pymerkle_logsTransparentes/__init__.py
pymerkle_logsTransparentes/constants.py
pymerkle_logsTransparentes/hashing.py
pymerkle_logsTransparentes/proof.py
pymerkle_logsTransparentes/utils.py
pymerkle_logsTransparentes/tree/__init__.py
pymerkle_logsTransparentes/tree/base.py
pymerkle_logsTransparentes/tree/sakura.py
pymerkle_logstransparentes-0.0.3.dist-info/METADATA
pymerkle_logstransparentes-0.0.3.dist-info/WHEEL
pymerkle_logstransparentes-0.0.3.dist-info/licenses/LICENSE
pymerkle_logstransparentes-0.0.3.dist-info/RECORD
