Metadata-Version: 2.1
Name: pymerkle-logsTransparentes
Version: 0.0.3
Summary: A Python implementation of Merkle Tree
Project-URL: Homepage, https://github.com/Guilherme-Fumagali/pymerkle
Project-URL: Bug Tracker, https://github.com/Guilherme-Fumagali/pymerkle/issues
Author-email: Guilherme Fumagali <guilhermefumarques@gmail.com>
License-File: LICENSE
Classifier: License :: OSI Approved :: MIT License
Classifier: Operating System :: OS Independent
Classifier: Programming Language :: Python :: 3
Requires-Python: >=3.7
